README.md
setup.cfg
setup.py
kant/__init__.py
kant/conftest.py
kant/exceptions.py
kant.egg-info/PKG-INFO
kant.egg-info/SOURCES.txt
kant.egg-info/dependency_links.txt
kant.egg-info/not-zip-safe
kant.egg-info/requires.txt
kant.egg-info/top_level.txt
kant/aggregates/__init__.py
kant/aggregates/base.py
kant/aggregates/exceptions.py
kant/datamapper/__init__.py
kant/datamapper/base.py
kant/datamapper/exceptions.py
kant/datamapper/fields.py
kant/datamapper/models.py
kant/events/__init__.py
kant/events/base.py
kant/events/exceptions.py
kant/eventstore/__init__.py
kant/eventstore/connection.py
kant/eventstore/exceptions.py
kant/eventstore/stream.py
kant/eventstore/backends/__init__.py
kant/eventstore/backends/aiopg.py
kant/projections/__init__.py
kant/projections/base.py
kant/projections/exceptions.py
kant/projections/sa.py