Metadata-Version: 1.1
Name: kant
Version: 2.0.2
Summary: The CQRS and Event Sourcing framework for Python
Home-page: http://github.com/patrickporto/kant
Author: Patrick Porto
Author-email: patrick.s.porto@gmail.com
License: MIT
Keywords: eventsourcing cqrs eventstore
Platform: UNKNOWN
Classifier: Development Status :: 3 - Alpha
Classifier: Intended Audience :: Developers
Classifier: Topic :: Software Development :: Libraries :: Python Modules
Classifier: License :: OSI Approved :: MIT License
Classifier: Programming Language :: Python :: 3.5
Classifier: Programming Language :: Python :: 3.6
Classifier: Programming Language :: Python :: Implementation :: CPython
